{
  "image_file": "bea479a6-ceb3-4aa5-b940-97fa81f71660.png",
  "error_bars": [
    {
      "lineName": "Drug_1500mg (N=3)",
      "points": [
        {
          "data_point": {
            "x": 295.49119135251885,
            "y": 363.37250182310555
          },
          "upper_error_bar": {
            "x": 295.49119135251885,
            "y": 363.0
          },
          "lower_error_bar": {
            "x": 295.49119135251885,
            "y": 363.0
          },
          "confidence": 0.07930641821946169
        },
        {
          "data_point": {
            "x": 551.9334005750088,
            "y": 537.2835477444219
          },
          "upper_error_bar": {
            "x": 551.9334005750088,
            "y": 533.0
          },
          "lower_error_bar": {
            "x": 551.9334005750088,
            "y": 535.0
          },
          "confidence": 0.5657556935817806
        },
        {
          "data_point": {
            "x": 691.0358800659541,
            "y": 541.7658379815042
          },
          "upper_error_bar": {
            "x": 691.0358800659541,
            "y": 535.0
          },
          "lower_error_bar": {
            "x": 691.0358800659541,
            "y": 538.0
          },
          "confidence": 0.6140062111801242
        },
        {
          "data_point": {
            "x": 830.181818181818,
            "y": 581.4474231828983
          },
          "upper_error_bar": {
            "x": 830.181818181818,
            "y": 577.0
          },
          "lower_error_bar": {
            "x": 830.181818181818,
            "y": 577.0
          },
          "confidence": 0.5966977225672878
        },
        {
          "data_point": {
            "x": 813.6754105007246,
            "y": 576.7401321786805
          },
          "upper_error_bar": {
            "x": 813.6754105007246,
            "y": 562.0
          },
          "lower_error_bar": {
            "x": 813.6754105007246,
            "y": 582.0
          },
          "confidence": 0.6501035196687371
        }
      ]
    },
    {
      "lineName": "Drug_3mg (N=4)",
      "points": [
        {
          "data_point": {
            "x": 262.74334609254504,
            "y": 346.94680627902665
          },
          "upper_error_bar": {
            "x": 262.74334609254504,
            "y": 347.0
          },
          "lower_error_bar": {
            "x": 262.74334609254504,
            "y": 347.0
          },
          "confidence": 0.0917287784679089
        },
        {
          "data_point": {
            "x": 381.6005875886453,
            "y": 480.59978880998693
          },
          "upper_error_bar": {
            "x": 381.6005875886453,
            "y": 460.0
          },
          "lower_error_bar": {
            "x": 381.6005875886453,
            "y": 482.0
          },
          "confidence": 0.6658592132505176
        },
        {
          "data_point": {
            "x": 471.69504762197363,
            "y": 502.55905306595037
          },
          "upper_error_bar": {
            "x": 471.69504762197363,
            "y": 481.0
          },
          "lower_error_bar": {
            "x": 471.69504762197363,
            "y": 531.0
          },
          "confidence": 0.7156314699792962
        },
        {
          "data_point": {
            "x": 596.7439920489251,
            "y": 549.6834540997282
          },
          "upper_error_bar": {
            "x": 596.7439920489251,
            "y": 548.0
          },
          "lower_error_bar": {
            "x": 596.7439920489251,
            "y": 565.0
          },
          "confidence": 0.6746066252587992
        },
        {
          "data_point": {
            "x": 713.444675205899,
            "y": 537.1128370820503
          },
          "upper_error_bar": {
            "x": 713.444675205899,
            "y": 536.0
          },
          "lower_error_bar": {
            "x": 713.444675205899,
            "y": 541.0
          },
          "confidence": 0.6297619047619047
        },
        {
          "data_point": {
            "x": 830.1818181818181,
            "y": 585.1781753982721
          },
          "upper_error_bar": {
            "x": 830.1818181818181,
            "y": 562.0
          },
          "lower_error_bar": {
            "x": 830.1818181818181,
            "y": 582.0
          },
          "confidence": 0.2095755599831788
        },
        {
          "data_point": {
            "x": 723.1871298339788,
            "y": 541.1241942713015
          },
          "upper_error_bar": {
            "x": 723.1871298339788,
            "y": 529.0
          },
          "lower_error_bar": {
            "x": 723.1871298339788,
            "y": 583.0
          },
          "confidence": 0.73472049689441
        },
        {
          "data_point": {
            "x": 672.3465931680341,
            "y": 541.5397884544274
          },
          "upper_error_bar": {
            "x": 672.3465931680341,
            "y": 535.0
          },
          "lower_error_bar": {
            "x": 672.3465931680341,
            "y": 548.0
          },
          "confidence": 0.6229089026915113
        },
        {
          "data_point": {
            "x": 652.8715745691251,
            "y": 543.63757394802
          },
          "upper_error_bar": {
            "x": 652.8715745691251,
            "y": 534.0
          },
          "lower_error_bar": {
            "x": 652.8715745691251,
            "y": 561.0
          },
          "confidence": 0.6415838509316771
        },
        {
          "data_point": {
            "x": 322.5918462245172,
            "y": 414.2454448975672
          },
          "upper_error_bar": {
            "x": 322.5918462245172,
            "y": 418.0
          },
          "lower_error_bar": {
            "x": 322.5918462245172,
            "y": 418.0
          },
          "confidence": 0.090175983436853
        }
      ]
    },
    {
      "lineName": "Line_98",
      "points": [
        {
          "data_point": {
            "x": 153.81818181818184,
            "y": 87.0497680819858
          },
          "upper_error_bar": {
            "x": 153.81818181818184,
            "y": 87.0
          },
          "lower_error_bar": {
            "x": 153.81818181818184,
            "y": 87.0
          },
          "confidence": 0.0016666666666666668
        },
        {
          "data_point": {
            "x": 262.74334609254504,
            "y": 403.37207585119467
          },
          "upper_error_bar": {
            "x": 262.74334609254504,
            "y": 406.0
          },
          "lower_error_bar": {
            "x": 262.74334609254504,
            "y": 418.0
          },
          "confidence": 0.6600621118012423
        },
        {
          "data_point": {
            "x": 381.6005875886453,
            "y": 481.8829221724221
          },
          "upper_error_bar": {
            "x": 381.6005875886453,
            "y": 460.0
          },
          "lower_error_bar": {
            "x": 381.6005875886453,
            "y": 482.0
          },
          "confidence": 0.6658592132505176
        },
        {
          "data_point": {
            "x": 471.69504762197363,
            "y": 506.31334083604304
          },
          "upper_error_bar": {
            "x": 471.69504762197363,
            "y": 481.0
          },
          "lower_error_bar": {
            "x": 471.69504762197363,
            "y": 531.0
          },
          "confidence": 0.7156314699792962
        },
        {
          "data_point": {
            "x": 713.444675205899,
            "y": 592.9151654949617
          },
          "upper_error_bar": {
            "x": 713.444675205899,
            "y": 593.0
          },
          "lower_error_bar": {
            "x": 713.444675205899,
            "y": 593.0
          },
          "confidence": 0.07309523809523809
        },
        {
          "data_point": {
            "x": 830.1818181818181,
            "y": 605.5196824210349
          },
          "upper_error_bar": {
            "x": 830.1818181818181,
            "y": 606.0
          },
          "lower_error_bar": {
            "x": 830.1818181818181,
            "y": 606.0
          },
          "confidence": 0.05756728778467909
        }
      ]
    },
    {
      "lineName": "Drug_10mg (N=3)",
      "points": [
        {
          "data_point": {
            "x": 153.81818181818184,
            "y": 314.4228052221724
          },
          "upper_error_bar": {
            "x": 153.81818181818184,
            "y": 304.0
          },
          "lower_error_bar": {
            "x": 153.81818181818184,
            "y": 331.0
          },
          "confidence": 0.6648757763975156
        },
        {
          "data_point": {
            "x": 471.69504762197363,
            "y": 531.5483579448878
          },
          "upper_error_bar": {
            "x": 471.69504762197363,
            "y": 532.0
          },
          "lower_error_bar": {
            "x": 471.69504762197363,
            "y": 532.0
          },
          "confidence": 0.6339648033126295
        },
        {
          "data_point": {
            "x": 596.7439920489251,
            "y": 560.4682080365518
          },
          "upper_error_bar": {
            "x": 596.7439920489251,
            "y": 548.0
          },
          "lower_error_bar": {
            "x": 596.7439920489251,
            "y": 565.0
          },
          "confidence": 0.6746066252587992
        },
        {
          "data_point": {
            "x": 713.444675205899,
            "y": 598.5397048237479
          },
          "upper_error_bar": {
            "x": 713.444675205899,
            "y": 599.0
          },
          "lower_error_bar": {
            "x": 713.444675205899,
            "y": 599.0
          },
          "confidence": 0.07309523809523809
        },
        {
          "data_point": {
            "x": 830.1818181818181,
            "y": 578.0016956637146
          },
          "upper_error_bar": {
            "x": 830.1818181818181,
            "y": 562.0
          },
          "lower_error_bar": {
            "x": 830.1818181818181,
            "y": 577.0
          },
          "confidence": 0.6200310559006211
        },
        {
          "data_point": {
            "x": 643.9807261802154,
            "y": 575.8783420911919
          },
          "upper_error_bar": {
            "x": 643.9807261802154,
            "y": 576.0
          },
          "lower_error_bar": {
            "x": 643.9807261802154,
            "y": 576.0
          },
          "confidence": 0.06222567287784679
        },
        {
          "data_point": {
            "x": 258.9523711731073,
            "y": 386.2346337301107
          },
          "upper_error_bar": {
            "x": 258.9523711731073,
            "y": 350.0
          },
          "lower_error_bar": {
            "x": 258.9523711731073,
            "y": 399.0
          },
          "confidence": 0.7263871635610767
        }
      ]
    },
    {
      "lineName": "Line_33",
      "points": [
        {
          "data_point": {
            "x": 153.81818181818184,
            "y": 280.8254605000883
          },
          "upper_error_bar": {
            "x": 153.81818181818184,
            "y": 283.0
          },
          "lower_error_bar": {
            "x": 153.81818181818184,
            "y": 331.0
          },
          "confidence": 0.2995979886891831
        },
        {
          "data_point": {
            "x": 262.74334609254504,
            "y": 357.05213503358607
          },
          "upper_error_bar": {
            "x": 262.74334609254504,
            "y": 357.0
          },
          "lower_error_bar": {
            "x": 262.74334609254504,
            "y": 357.0
          },
          "confidence": 0.0917287784679089
        },
        {
          "data_point": {
            "x": 381.6005875886453,
            "y": 498.92081373240944
          },
          "upper_error_bar": {
            "x": 381.6005875886453,
            "y": 482.0
          },
          "lower_error_bar": {
            "x": 381.6005875886453,
            "y": 506.0
          },
          "confidence": 0.669192546583851
        },
        {
          "data_point": {
            "x": 471.69504762197363,
            "y": 502.4866641348126
          },
          "upper_error_bar": {
            "x": 471.69504762197363,
            "y": 481.0
          },
          "lower_error_bar": {
            "x": 471.69504762197363,
            "y": 531.0
          },
          "confidence": 0.7156314699792962
        },
        {
          "data_point": {
            "x": 596.7439920489251,
            "y": 530.2408652852438
          },
          "upper_error_bar": {
            "x": 596.7439920489251,
            "y": 518.0
          },
          "lower_error_bar": {
            "x": 596.7439920489251,
            "y": 537.0
          },
          "confidence": 0.6779399585921325
        },
        {
          "data_point": {
            "x": 713.444675205899,
            "y": 580.2329890468284
          },
          "upper_error_bar": {
            "x": 713.444675205899,
            "y": 545.0
          },
          "lower_error_bar": {
            "x": 713.444675205899,
            "y": 583.0
          },
          "confidence": 0.39753966064153623
        },
        {
          "data_point": {
            "x": 830.1818181818181,
            "y": 573.3416106458578
          },
          "upper_error_bar": {
            "x": 830.1818181818181,
            "y": 562.0
          },
          "lower_error_bar": {
            "x": 830.1818181818181,
            "y": 577.0
          },
          "confidence": 0.6200310559006211
        },
        {
          "data_point": {
            "x": 549.8807138637948,
            "y": 519.8397151173708
          },
          "upper_error_bar": {
            "x": 549.8807138637948,
            "y": 520.0
          },
          "lower_error_bar": {
            "x": 549.8807138637948,
            "y": 520.0
          },
          "confidence": 0.010983436853002071
        }
      ]
    }
  ]
}