{
  "image_file": "bf84f433-174b-4e03-9647-26a5084d0503.png",
  "error_bars": [
    {
      "lineName": "Drug_100mg (N=4)",
      "points": [
        {
          "data_point": {
            "x": 250.22901012107218,
            "y": 300.5519387032306
          },
          "upper_error_bar": {
            "x": 250.22901012107218,
            "y": 301.0
          },
          "lower_error_bar": {
            "x": 250.22901012107218,
            "y": 301.0
          },
          "confidence": 0.0016666666666666668
        },
        {
          "data_point": {
            "x": 330.26724454968075,
            "y": 402.3435602713569
          },
          "upper_error_bar": {
            "x": 330.26724454968075,
            "y": 402.0
          },
          "lower_error_bar": {
            "x": 330.26724454968075,
            "y": 402.0
          },
          "confidence": 0.0016666666666666668
        },
        {
          "data_point": {
            "x": 426.3996254841469,
            "y": 456.9588965594871
          },
          "upper_error_bar": {
            "x": 426.3996254841469,
            "y": 457.0
          },
          "lower_error_bar": {
            "x": 426.3996254841469,
            "y": 457.0
          },
          "confidence": 0.0016666666666666668
        },
        {
          "data_point": {
            "x": 529.4145593117897,
            "y": 522.3605064406472
          },
          "upper_error_bar": {
            "x": 529.4145593117897,
            "y": 522.0
          },
          "lower_error_bar": {
            "x": 529.4145593117897,
            "y": 522.0
          },
          "confidence": 0.0016666666666666668
        },
        {
          "data_point": {
            "x": 631.33771490467,
            "y": 586.6635327065178
          },
          "upper_error_bar": {
            "x": 631.33771490467,
            "y": 587.0
          },
          "lower_error_bar": {
            "x": 631.33771490467,
            "y": 587.0
          },
          "confidence": 0.014089026915113871
        },
        {
          "data_point": {
            "x": 830.1818181818181,
            "y": 608.5784546365157
          },
          "upper_error_bar": {
            "x": 830.1818181818181,
            "y": 609.0
          },
          "lower_error_bar": {
            "x": 830.1818181818181,
            "y": 609.0
          },
          "confidence": 0.0016666666666666668
        },
        {
          "data_point": {
            "x": 295.6564972545679,
            "y": 333.6494387983846
          },
          "upper_error_bar": {
            "x": 295.6564972545679,
            "y": 334.0
          },
          "lower_error_bar": {
            "x": 295.6564972545679,
            "y": 334.0
          },
          "confidence": 0.0016666666666666668
        },
        {
          "data_point": {
            "x": 390.45624078240945,
            "y": 428.8932809392028
          },
          "upper_error_bar": {
            "x": 390.45624078240945,
            "y": 429.0
          },
          "lower_error_bar": {
            "x": 390.45624078240945,
            "y": 429.0
          },
          "confidence": 0.0016666666666666668
        },
        {
          "data_point": {
            "x": 252.77557594978515,
            "y": 301.9089392914438
          },
          "upper_error_bar": {
            "x": 252.77557594978515,
            "y": 302.0
          },
          "lower_error_bar": {
            "x": 252.77557594978515,
            "y": 302.0
          },
          "confidence": 0.0016666666666666668
        },
        {
          "data_point": {
            "x": 248.67003489578428,
            "y": 272.72776654913207
          },
          "upper_error_bar": {
            "x": 248.67003489578428,
            "y": 273.0
          },
          "lower_error_bar": {
            "x": 248.67003489578428,
            "y": 273.0
          },
          "confidence": 0.024958592132505175
        }
      ]
    },
    {
      "lineName": "Line_41",
      "points": [
        {
          "data_point": {
            "x": 153.8181818181818,
            "y": 108.17765184834877
          },
          "upper_error_bar": {
            "x": 153.8181818181818,
            "y": 110.0
          },
          "lower_error_bar": {
            "x": 153.8181818181818,
            "y": 144.0
          },
          "confidence": 0.2259714980390447
        },
        {
          "data_point": {
            "x": 250.22901012107218,
            "y": 285.35099483686815
          },
          "upper_error_bar": {
            "x": 250.22901012107218,
            "y": 285.0
          },
          "lower_error_bar": {
            "x": 250.22901012107218,
            "y": 285.0
          },
          "confidence": 0.007877846790890269
        },
        {
          "data_point": {
            "x": 330.26724454968075,
            "y": 334.70087885925
          },
          "upper_error_bar": {
            "x": 330.26724454968075,
            "y": 335.0
          },
          "lower_error_bar": {
            "x": 330.26724454968075,
            "y": 335.0
          },
          "confidence": 0.0016666666666666668
        },
        {
          "data_point": {
            "x": 426.3996254841469,
            "y": 474.1215815844735
          },
          "upper_error_bar": {
            "x": 426.3996254841469,
            "y": 474.0
          },
          "lower_error_bar": {
            "x": 426.3996254841469,
            "y": 474.0
          },
          "confidence": 0.0016666666666666668
        },
        {
          "data_point": {
            "x": 529.4145593117897,
            "y": 535.7797074590012
          },
          "upper_error_bar": {
            "x": 529.4145593117897,
            "y": 536.0
          },
          "lower_error_bar": {
            "x": 529.4145593117897,
            "y": 536.0
          },
          "confidence": 0.0016666666666666668
        },
        {
          "data_point": {
            "x": 746.1637035044713,
            "y": 572.3811187212278
          },
          "upper_error_bar": {
            "x": 746.1637035044713,
            "y": 572.0
          },
          "lower_error_bar": {
            "x": 746.1637035044713,
            "y": 572.0
          },
          "confidence": 0.03582815734989648
        },
        {
          "data_point": {
            "x": 830.1818181818181,
            "y": 612.3784592285882
          },
          "upper_error_bar": {
            "x": 830.1818181818181,
            "y": 612.0
          },
          "lower_error_bar": {
            "x": 830.1818181818181,
            "y": 612.0
          },
          "confidence": 0.0016666666666666668
        }
      ]
    },
    {
      "lineName": "Line_54",
      "points": [
        {
          "data_point": {
            "x": 153.8181818181818,
            "y": 113.82106542086603
          },
          "upper_error_bar": {
            "x": 153.8181818181818,
            "y": 110.0
          },
          "lower_error_bar": {
            "x": 153.8181818181818,
            "y": 144.0
          },
          "confidence": 0.6703312629399586
        },
        {
          "data_point": {
            "x": 330.26724454968075,
            "y": 410.9580286391975
          },
          "upper_error_bar": {
            "x": 330.26724454968075,
            "y": 411.0
          },
          "lower_error_bar": {
            "x": 330.26724454968075,
            "y": 411.0
          },
          "confidence": 0.0016666666666666668
        },
        {
          "data_point": {
            "x": 426.3996254841469,
            "y": 465.8150879269176
          },
          "upper_error_bar": {
            "x": 426.3996254841469,
            "y": 466.0
          },
          "lower_error_bar": {
            "x": 426.3996254841469,
            "y": 466.0
          },
          "confidence": 0.0016666666666666668
        },
        {
          "data_point": {
            "x": 529.4145593117897,
            "y": 580.566092096917
          },
          "upper_error_bar": {
            "x": 529.4145593117897,
            "y": 581.0
          },
          "lower_error_bar": {
            "x": 529.4145593117897,
            "y": 581.0
          },
          "confidence": 0.007877846790890269
        },
        {
          "data_point": {
            "x": 746.1637035044713,
            "y": 607.1523465906415
          },
          "upper_error_bar": {
            "x": 746.1637035044713,
            "y": 607.0
          },
          "lower_error_bar": {
            "x": 746.1637035044713,
            "y": 607.0
          },
          "confidence": 0.03582815734989648
        },
        {
          "data_point": {
            "x": 830.1818181818181,
            "y": 591.201586985293
          },
          "upper_error_bar": {
            "x": 830.1818181818181,
            "y": 591.0
          },
          "lower_error_bar": {
            "x": 830.1818181818181,
            "y": 591.0
          },
          "confidence": 0.0016666666666666668
        },
        {
          "data_point": {
            "x": 660.710930275285,
            "y": 594.7727173906724
          },
          "upper_error_bar": {
            "x": 660.710930275285,
            "y": 595.0
          },
          "lower_error_bar": {
            "x": 660.710930275285,
            "y": 595.0
          },
          "confidence": 0.052908902691511384
        },
        {
          "data_point": {
            "x": 739.4036316705906,
            "y": 606.0411513426862
          },
          "upper_error_bar": {
            "x": 739.4036316705906,
            "y": 606.0
          },
          "lower_error_bar": {
            "x": 739.4036316705906,
            "y": 606.0
          },
          "confidence": 0.0016666666666666668
        },
        {
          "data_point": {
            "x": 237.19300865407106,
            "y": 142.96428578807877
          },
          "upper_error_bar": {
            "x": 237.19300865407106,
            "y": 143.0
          },
          "lower_error_bar": {
            "x": 237.19300865407106,
            "y": 143.0
          },
          "confidence": 0.0016666666666666668
        },
        {
          "data_point": {
            "x": 643.3302183622068,
            "y": 592.6185505664448
          },
          "upper_error_bar": {
            "x": 643.3302183622068,
            "y": 593.0
          },
          "lower_error_bar": {
            "x": 643.3302183622068,
            "y": 593.0
          },
          "confidence": 0.007877846790890269
        }
      ]
    }
  ]
}